{
  "project_info": {
    "project_number": "965858215724",
    "project_id": "weev-app",
    "storage_bucket": "weev-app.firebasestorage.app"
  },
  "client": [
    {
      "client_info": {
        "mobilesdk_app_id": "1:965858215724:android:676614beae93e2ca0c0e89",
        "android_client_info": {
          "package_name": "com.company.weevapp"
        }
      },
      "oauth_client": [
        {
          "client_id": "965858215724-q32iv7rrvq784a6e5srd1u7libddnapu.apps.googleusercontent.com",
          "client_type": 3
        }
      ],
      "api_key": [
        {
          "current_key": "AIzaSyCZCMX0BNJLz3iyDRcI2_e7ciiWpB2pOdc"
        }
      ],
      "services": {
        "appinvite_service": {
          "other_platform_oauth_client": [
            {
              "client_id": "965858215724-q32iv7rrvq784a6e5srd1u7libddnapu.apps.googleusercontent.com",
              "client_type": 3
            }
          ]
        }
      }
    }
  ],
  "configuration_version": "1"
}